hello_world/__init__.py
hello_world/tools/__init__.py
hello_world/tools/hello_world_tool.py
hello_world/tools/utils.py
hello_world/yamls/hello_world_tool.yaml
tests/__init__.py
tests/test_hello_world_tool.py
hello_world_th-0.0.2.dist-info/METADATA
hello_world_th-0.0.2.dist-info/WHEEL
hello_world_th-0.0.2.dist-info/entry_points.txt
hello_world_th-0.0.2.dist-info/top_level.txt
hello_world_th-0.0.2.dist-info/RECORD
