Metadata-Version: 2.1
Name: hello_world_th
Version: 0.0.2
Summary: This is my tools package
